mahiru/nuzlocke/__init__.py
mahiru/nuzlocke/badges.py
mahiru/nuzlocke/module.py
mahiru/nuzlocke/state.py
mahiru/nuzlocke/website.py
mahiru/nuzlocke/templates/display.html
mahiru/nuzlocke/templates/rules.html
mahiru/nuzlocke/templates/smooth.html
mahiru_nuzlocke-0.0.2.dist-info/METADATA
mahiru_nuzlocke-0.0.2.dist-info/WHEEL
mahiru_nuzlocke-0.0.2.dist-info/top_level.txt
mahiru_nuzlocke-0.0.2.dist-info/RECORD
